[
  {
    "id": 1,
    "title": "Tikur Fiker",
    "amharic_title": "ጥቁር ፍቅር",
    "poster": "https://marziplus8-wq.github.io/Kana/photo/tikurfiker.png",
    "banner": "https://marziplus8-wq.github.io/Kana/photo/tikurfiker.png",
    "description": "Ömer is a police officer who wants to unveil the truth about the possible murder of his fiancée, who committed suicide.",
    "genre": "Drama",
    "country": "South Korea",
    "language": "Korean",
    "video_link": "https://pub-6d94be894a8b4e14a6472bfe42a2257e.r2.dev/tikurfiker",
    "releaseYear": 2024,
    "rating": 9.9,
    "parts": 162,
    "views": 1254300,
    "featured": true
  },
  {
    "id": 2,
    "title": "Twenty-Five Twenty-One",
    "amharic_title": "የፍቅር ዘመን 24-21",
    "poster": "https://marziplus8-wq.github.io/Kana/photo/tfto.png",
    "banner": "https://marziplus8-wq.github.io/Kana/photo/tfto.png",
    "description": "A story about the complexities of love and relationships in modern times.",
    "genre": "Romance",
    "country": "South Korea",
    "language": "Korean",
    "video_link": "https://pub-6d94be894a8b4e14a6472bfe42a2257e.r2.dev/tfto",
    "releaseYear": 2023,
    "rating": 9.9,
    "parts": 16,
    "views": 983500,
    "featured": false
  },
  {
    "id": 3,
    "title": "City of Shadows",
    "poster": "https://upload.wikimedia.org/wikipedia/en/e/e0/Kuzgun_series_poster.jpg",
    "banner": "https://upload.wikimedia.org/wikipedia/en/e/e0/Kuzgun_series_poster.jpg",
    "description": "An honest detective battles corruption in a city ruled by crime.",
    "genre": "Crime",
    "country": "Turkey",
    "language": "Turkish",
    "video_link": "https://pub-6d94be894a8b4e14a6472bfe42a2257e.r2.dev/city-of-shadows",
    "releaseYear": 2022,
    "rating": 8.7,
    "parts": 18,
    "views": 745200,
    "featured": true
  },
  {
    "id": 4,
    "title": "The Last Kingdom",
    "poster": "https://encrypted-tbn0.gstatic.com/images?q=tbn:ANd9GcRLAfgDmK7SR2VAP0p-AWgtpuGjIvIHEy9ZfsVM6Bxpgg&s=10",
    "banner": "https://encrypted-tbn0.gstatic.com/images?q=tbn:ANd9GcRLAfgDmK7SR2VAP0p-AWgtpuGjIvIHEy9ZfsVM6Bxpgg&s=10",
    "description": "A prince fights to reclaim his kingdom from ruthless invaders.",
    "genre": "Historical",
    "country": "United Kingdom",
    "language": "English",
    "video_link": "https://pub-6d94be894a8b4e14a6472bfe42a2257e.r2.dev/the-last-kingdom",
    "releaseYear": 2021,
    "rating": 9.1,
    "parts": 20,
    "views": 2150000,
    "featured": false
  },
  {
    "id": 5,
    "title": "Dream Chasers",
    "poster": "https://encrypted-tbn0.gstatic.com/images?q=tbn:ANd9GcSGF9tHBnIKmcPqx63vr7eVFNSIsM9OfGfLR3PU6SODZXus6_u8eI5gq2mG&s=10",
    "banner": "https://encrypted-tbn0.gstatic.com/images?q=tbn:ANd9GcSGF9tHBnIKmcPqx63vr7eVFNSIsM9OfGfLR3PU6SODZXus6_u8eI5gq2mG&s=10",
    "description": "Five friends pursue their dreams while facing life's challenges.",
    "genre": "Drama",
    "country": "Japan",
    "language": "Japanese",
    "video_link": "https://pub-6d94be894a8b4e14a6472bfe42a2257e.r2.dev/dream-chasers",
    "releaseYear": 2025,
    "rating": 8.3,
    "parts": 12,
    "views": 432000,
    "featured": false
  },
  {
    "id": 6,
    "title": "Dark Horizon",
    "poster": "https://bestsimilar.com/img/movie/thumb/f6/109056.jpg",
    "banner": "https://bestsimilar.com/img/movie/thumb/f6/109056.jpg",
    "description": "Survivors struggle to rebuild civilization after a global disaster.",
    "genre": "Sci-Fi",
    "country": "United States",
    "language": "English",
    "video_link": "https://pub-6d94be894a8b4e14a6472bfe42a2257e.r2.dev/dark-horizon",
    "releaseYear": 2025,
    "rating": 9.0,
    "parts": 10,
    "views": 1876000,
    "featured": true
  }
]
